mcp_ticketer/__init__.py
mcp_ticketer/__version__.py
mcp_ticketer/_version_scm.py
mcp_ticketer/py.typed
mcp_ticketer/adapters/__init__.py
mcp_ticketer/adapters/aitrackdown.py
mcp_ticketer/adapters/hybrid.py
mcp_ticketer/adapters/linear.py
mcp_ticketer/adapters/asana/__init__.py
mcp_ticketer/adapters/asana/adapter.py
mcp_ticketer/adapters/asana/client.py
mcp_ticketer/adapters/asana/mappers.py
mcp_ticketer/adapters/asana/types.py
mcp_ticketer/adapters/github/__init__.py
mcp_ticketer/adapters/github/adapter.py
mcp_ticketer/adapters/github/client.py
mcp_ticketer/adapters/github/mappers.py
mcp_ticketer/adapters/github/queries.py
mcp_ticketer/adapters/github/types.py
mcp_ticketer/adapters/jira/__init__.py
mcp_ticketer/adapters/jira/adapter.py
mcp_ticketer/adapters/jira/client.py
mcp_ticketer/adapters/jira/mappers.py
mcp_ticketer/adapters/jira/queries.py
mcp_ticketer/adapters/jira/types.py
mcp_ticketer/adapters/linear/__init__.py
mcp_ticketer/adapters/linear/adapter.py
mcp_ticketer/adapters/linear/client.py
mcp_ticketer/adapters/linear/mappers.py
mcp_ticketer/adapters/linear/queries.py
mcp_ticketer/adapters/linear/types.py
mcp_ticketer/analysis/__init__.py
mcp_ticketer/analysis/dependency_graph.py
mcp_ticketer/analysis/health_assessment.py
mcp_ticketer/analysis/orphaned.py
mcp_ticketer/analysis/project_status.py
mcp_ticketer/analysis/similarity.py
mcp_ticketer/analysis/staleness.py
mcp_ticketer/automation/__init__.py
mcp_ticketer/automation/project_updates.py
mcp_ticketer/cache/__init__.py
mcp_ticketer/cache/memory.py
mcp_ticketer/cli/__init__.py
mcp_ticketer/cli/adapter_diagnostics.py
mcp_ticketer/cli/auggie_configure.py
mcp_ticketer/cli/codex_configure.py
mcp_ticketer/cli/configure.py
mcp_ticketer/cli/cursor_configure.py
mcp_ticketer/cli/diagnostics.py
mcp_ticketer/cli/discover.py
mcp_ticketer/cli/gemini_configure.py
mcp_ticketer/cli/init_command.py
mcp_ticketer/cli/install_mcp_server.py
mcp_ticketer/cli/instruction_commands.py
mcp_ticketer/cli/linear_commands.py
mcp_ticketer-2.3.11.dist-info/licenses/LICENSE
mcp_ticketer-2.3.11.dist-info/METADATA
mcp_ticketer-2.3.11.dist-info/WHEEL
mcp_ticketer-2.3.11.dist-info/entry_points.txt
mcp_ticketer-2.3.11.dist-info/top_level.txt
mcp_ticketer-2.3.11.dist-info/RECORD
