Metadata-Version: 2.4
Name: mcp-ticketer
Version: 2.3.11
Summary: Universal ticket management interface for AI agents with MCP support
Author-email: MCP Ticketer Team <support@mcp-ticketer.io>
Maintainer-email: MCP Ticketer Team <support@mcp-ticketer.io>
License-Expression: MIT
Project-URL: Homepage, https://github.com/mcp-ticketer/mcp-ticketer
Project-URL: Documentation, https://mcp-ticketer.readthedocs.io
Project-URL: Repository, https://github.com/mcp-ticketer/mcp-ticketer
Project-URL: Issues, https://github.com/mcp-ticketer/mcp-ticketer/issues
Project-URL: Changelog, https://github.com/mcp-ticketer/mcp-ticketer/blob/main/CHANGELOG.md
Keywords: mcp,tickets,jira,linear,github,issue-tracking,project-management,ai,automation,agent,ticketing
Classifier: Development Status :: 4 - Beta
Classifier: Intended Audience :: Developers
Classifier: Intended Audience :: System Administrators
Classifier: Operating System :: OS Independent
Classifier: Programming Language :: Python
Classifier: Programming Language :: Python :: 3
Classifier: Programming Language :: Python :: 3.10
Classifier: Programming Language :: Python :: 3.11
Classifier: Programming Language :: Python :: 3.12
Classifier: Programming Language :: Python :: 3.13
Classifier: Programming Language :: Python :: Implementation :: CPython
Classifier: Topic :: Software Development :: Libraries
Classifier: Topic :: Software Development :: Libraries :: Python Modules
Classifier: Topic :: Software Development :: Bug Tracking
Classifier: Topic :: System :: Monitoring
Classifier: Topic :: Internet :: WWW/HTTP
Classifier: Typing :: Typed
Requires-Python: >=3.10
License-File: LICENSE
Requires-Dist: gql[httpx]>=3.0.0
Requires-Dist: httpx>=0.25.0
Requires-Dist: mcp>=1.2.0
Requires-Dist: psutil>=5.9.0
Requires-Dist: pydantic>=2.0
Requires-Dist: python-dotenv>=1.0.0
Requires-Dist: pyyaml>=6.0.0
Requires-Dist: rich>=13.0.0
Requires-Dist: tomli>=2.0.0; python_version < "3.11"
Requires-Dist: tomli-w>=1.0.0
Requires-Dist: typer>=0.9.0
Requires-Dist: typing-extensions>=4.8.0
Provides-Extra: all
Requires-Dist: mcp-ticketer[analysis,github,jira,linear,mcp]; extra == "all"
Provides-Extra: dev
Requires-Dist: pytest>=7.4.0; extra == "dev"
Requires-Dist: pytest-asyncio>=0.21.0; extra == "dev"
Requires-Dist: pytest-cov>=4.1.0; extra == "dev"
Requires-Dist: pytest-timeout>=2.2.0; extra == "dev"
Requires-Dist: pytest-mock>=3.12.0; extra == "dev"
Requires-Dist: pytest-xdist>=3.0.0; extra == "dev"
Requires-Dist: black>=23.0.0; extra == "dev"
Requires-Dist: ruff>=0.1.0; extra == "dev"
Requires-Dist: mypy>=1.5.0; extra == "dev"
Requires-Dist: types-PyYAML>=6.0.0; extra == "dev"
Requires-Dist: tox>=4.11.0; extra == "dev"
Requires-Dist: pre-commit>=3.5.0; extra == "dev"
Requires-Dist: bump2version>=1.0.1; extra == "dev"
Requires-Dist: build>=1.0.0; extra == "dev"
Requires-Dist: twine>=5.0.0; extra == "dev"
Provides-Extra: docs
Requires-Dist: sphinx>=7.2.0; extra == "docs"
Requires-Dist: sphinx-rtd-theme>=2.0.0; extra == "docs"
Requires-Dist: sphinx-autodoc-typehints>=1.25.0; extra == "docs"
Requires-Dist: sphinx-click>=5.1.0; extra == "docs"
Requires-Dist: myst-parser>=2.0.0; extra == "docs"
Provides-Extra: mcp
Requires-Dist: mcp>=1.2.0; extra == "mcp"
Provides-Extra: jira
Requires-Dist: jira>=3.5.0; extra == "jira"
Requires-Dist: ai-trackdown-pytools>=1.5.0; extra == "jira"
Provides-Extra: linear
Requires-Dist: gql[httpx]>=3.0.0; extra == "linear"
Provides-Extra: github
Requires-Dist: PyGithub>=2.1.0; extra == "github"
Provides-Extra: analysis
Requires-Dist: scikit-learn>=1.3.0; extra == "analysis"
Requires-Dist: rapidfuzz>=3.0.0; extra == "analysis"
Requires-Dist: numpy>=1.24.0; extra == "analysis"
Provides-Extra: test
Requires-Dist: pytest>=7.4.0; extra == "test"
Requires-Dist: pytest-asyncio>=0.21.0; extra == "test"
Requires-Dist: pytest-cov>=4.1.0; extra == "test"
Requires-Dist: pytest-timeout>=2.2.0; extra == "test"
Requires-Dist: pytest-mock>=3.12.0; extra == "test"
Requires-Dist: pytest-xdist>=3.0.0; extra == "test"
Requires-Dist: responses>=0.24.0; extra == "test"
Dynamic: license-file
